{
  "scraped_at": "2026-05-25 23:17 UTC",
  "total": 1,
  "new_count": 1,
  "jobs": [
    {
      "company": "NavLogic AI",
      "title": "AI Engineer",
      "location": "Palo Alto, CA",
      "url": "https://www.linkedin.com/jobs/view/4415728279/",
      "date_posted": "2026-05-25",
      "ats": "LinkedIn"
    }
  ],
  "new_jobs": [
    {
      "company": "NavLogic AI",
      "title": "AI Engineer",
      "location": "Palo Alto, CA",
      "url": "https://www.linkedin.com/jobs/view/4415728279/",
      "date_posted": "2026-05-25",
      "ats": "LinkedIn"
    }
  ]
}